deveal/__init__.py
deveal/__main__.py
deveal/about.py
deveal/skeleton/deveal-index.html
deveal/skeleton/deveal.css
deveal/skeleton/deveal.yaml
deveal/skeleton/sections/part1.html
deveal/skeleton/sections/part2.html
deveal/skeleton/sections/title.html
deveal-1.3.0.dist-info/LICENSE
deveal-1.3.0.dist-info/METADATA
deveal-1.3.0.dist-info/WHEEL
deveal-1.3.0.dist-info/entry_points.txt
deveal-1.3.0.dist-info/top_level.txt
deveal-1.3.0.dist-info/RECORD
