Metadata-Version: 2.1
Name: deveal
Version: 1.3.0
Summary: A reveal.js helper tool
Home-page: https://github.com/jctophefabre/deveal
Author: Jean-Christophe Fabre
Author-email: jctophe.fabre@gmail.com
License: GPLv3
Platform: UNKNOWN
Requires-Python: ~=3.5
License-File: LICENSE
Requires-Dist: argparse
Requires-Dist: jinja2 (>=2.7)
Requires-Dist: PyYAML
Requires-Dist: watchdog
Requires-Dist: livereload
